[
{
    "timestamp": "2025-05-26T02:28:05.928Z",
    "level": "WARNING",
    "type": "slurm",
    "message": "Node node003 approaching memory limit: 91%",
    "source": "slurm-generator",
    "details": {
      "node": "node003",
      "percentage": "91"
    }
  },
{
    "timestamp": "2025-05-26T02:28:09.928Z",
    "level": "WARNING",
    "type": "slurm",
    "message": "Node node003 approaching memory limit: 93%",
    "source": "slurm-generator",
    "details": {
      "node": "node003",
      "percentage": "93"
    }
  },
{
    "timestamp": "2025-05-26T02:28:13.928Z",
    "level": "WARNING",
    "type": "slurm",
    "message": "Node node004 approaching memory limit: 87%",
    "source": "slurm-generator",
    "details": {
      "node": "node004",
      "percentage": "87"
    }
  },
{
    "timestamp": "2025-05-26T02:28:17.928Z",
    "level": "INFO",
    "type": "slurm",
    "message": "Job 4148 submitted by root at 2025-05-26T02:28:17.928Z",
    "source": "slurm-generator",
    "details": {
      "job_id": "4148",
      "user": "root"
    }
  },
{
    "timestamp": "2025-05-26T02:28:21.928Z",
    "level": "INFO",
    "type": "slurm",
    "message": "Job 7812 submitted by scheduler at 2025-05-26T02:28:21.928Z",
    "source": "slurm-generator",
    "details": {
      "job_id": "7812",
      "user": "scheduler"
    }
  },
{
    "timestamp": "2025-05-26T02:28:25.928Z",
    "level": "WARNING",
    "type": "slurm",
    "message": "Node node001 approaching memory limit: 86%",
    "source": "slurm-generator",
    "details": {
      "node": "node001",
      "percentage": "86"
    }
  },
{
    "timestamp": "2025-05-26T02:28:29.928Z",
    "level": "NOTICE",
    "type": "slurm",
    "message": "Scheduler configuration reloaded at 2025-05-26T02:28:29.928Z",
    "source": "slurm-generator"
  },
{
    "timestamp": "2025-05-26T02:28:33.928Z",
    "level": "WARNING",
    "type": "slurm",
    "message": "Node node001 approaching memory limit: 86%",
    "source": "slurm-generator",
    "details": {
      "node": "node001",
      "percentage": "86"
    }
  },
{
    "timestamp": "2025-05-26T02:28:37.928Z",
    "level": "INFO",
    "type": "slurm",
    "message": "Job 9718 submitted by root at 2025-05-26T02:28:37.928Z",
    "source": "slurm-generator",
    "details": {
      "job_id": "9718",
      "user": "root"
    }
  },
{
    "timestamp": "2025-05-26T02:28:41.928Z",
    "level": "NOTICE",
    "type": "slurm",
    "message": "Scheduler configuration reloaded at 2025-05-26T02:28:41.928Z",
    "source": "slurm-generator"
  },
{
    "timestamp": "2025-05-26T02:28:45.929Z",
    "level": "WARNING",
    "type": "slurm",
    "message": "Node node004 approaching memory limit: 93%",
    "source": "slurm-generator",
    "details": {
      "node": "node004",
      "percentage": "93"
    }
  },
{
    "timestamp": "2025-05-26T02:28:49.928Z",
    "level": "INFO",
    "type": "slurm",
    "message": "Reservation res_438 created for 10 hours",
    "source": "slurm-generator",
    "details": {
      "reservation_id": "res_438",
      "time_period": "10 hours"
    }
  }
]